{
  "calibration": {
    "imagePoints": [
      {
        "x": 0.14012490241998438,
        "y": 0.46549079754601225
      },
      {
        "x": 0.343871975019516,
        "y": 0.821319018404908
      },
      {
        "x": 0.689695550351288,
        "y": 0.3366564417177914
      },
      {
        "x": 0.773224043715847,
        "y": 0.522239263803681
      }
    ],
    "mapPoints": [
      {
        "lat": 48.11161481184071,
        "lng": 16.844755411148075
      },
      {
        "lat": 48.10465146958753,
        "lng": 16.868648529052738
      },
      {
        "lat": 48.12679907558873,
        "lng": 16.892724037170414
      },
      {
        "lat": 48.12278857416296,
        "lng": 16.9035816192627
      }
    ],
    "imageDimensions": {
      "width": 1281,
      "height": 652
    },
    "fullBounds": [
      [
        48.09225904561165,
        16.825606123328065
      ],
      [
        48.14371080835629,
        16.933458730446084
      ]
    ]
  },
  "layers": {
    "Auxiliarkastell": {
      "color": "#e74c3c",
      "geojson": {
        "type": "FeatureCollection",
        "features": [
          {
            "type": "Feature",
            "properties": {
              "layer": "Auxiliarkastell"
            },
            "geometry": {
              "type": "Polygon",
              "coordinates": [
                [
                  [
                    16.873906,
                    48.114638
                  ],
                  [
                    16.875644,
                    48.115605
                  ],
                  [
                    16.877489,
                    48.114251
                  ],
                  [
                    16.875772,
                    48.113162
                  ],
                  [
                    16.873906,
                    48.114638
                  ]
                ]
              ]
            }
          }
        ]
      }
    },
    "Gräberstraße": {
      "color": "#3498db",
      "geojson": {
        "type": "FeatureCollection",
        "features": [
          {
            "type": "Feature",
            "properties": {
              "layer": "Gräberstraße"
            },
            "geometry": {
              "type": "Polygon",
              "coordinates": [
                [
                  [
                    16.885879,
                    48.120941
                  ],
                  [
                    16.886265,
                    48.120841
                  ],
                  [
                    16.886137,
                    48.12054
                  ],
                  [
                    16.882145,
                    48.116271
                  ],
                  [
                    16.881759,
                    48.115067
                  ],
                  [
                    16.879635,
                    48.113234
                  ],
                  [
                    16.878798,
                    48.113549
                  ],
                  [
                    16.877232,
                    48.111758
                  ],
                  [
                    16.877146,
                    48.110827
                  ],
                  [
                    16.87618,
                    48.110641
                  ],
                  [
                    16.868048,
                    48.101499
                  ],
                  [
                    16.867447,
                    48.101585
                  ],
                  [
                    16.865044,
                    48.099092
                  ],
                  [
                    16.864314,
                    48.099521
                  ],
                  [
                    16.877832,
                    48.113535
                  ],
                  [
                    16.881866,
                    48.117259
                  ],
                  [
                    16.885879,
                    48.120941
                  ]
                ]
              ]
            }
          }
        ]
      }
    },
    "Legionslager": {
      "color": "#2ecc71",
      "geojson": {
        "type": "FeatureCollection",
        "features": [
          {
            "type": "Feature",
            "properties": {
              "layer": "Legionslager"
            },
            "geometry": {
              "type": "Polygon",
              "coordinates": [
                [
                  [
                    16.889527,
                    48.120769
                  ],
                  [
                    16.893282,
                    48.122903
                  ],
                  [
                    16.892273,
                    48.124894
                  ],
                  [
                    16.890943,
                    48.125224
                  ],
                  [
                    16.891286,
                    48.125739
                  ],
                  [
                    16.890707,
                    48.126398
                  ],
                  [
                    16.890149,
                    48.126541
                  ],
                  [
                    16.889505,
                    48.126427
                  ],
                  [
                    16.889098,
                    48.12594
                  ],
                  [
                    16.888862,
                    48.125381
                  ],
                  [
                    16.888626,
                    48.124923
                  ],
                  [
                    16.887617,
                    48.124908
                  ],
                  [
                    16.887617,
                    48.124522
                  ],
                  [
                    16.886544,
                    48.123662
                  ],
                  [
                    16.887145,
                    48.123261
                  ],
                  [
                    16.888368,
                    48.121872
                  ],
                  [
                    16.889527,
                    48.120769
                  ]
                ]
              ]
            }
          }
        ]
      }
    },
    "Gardelager": {
      "color": "#f39c12",
      "geojson": {
        "type": "FeatureCollection",
        "features": [
          {
            "type": "Feature",
            "properties": {
              "layer": "Gardelager"
            },
            "geometry": {
              "type": "Polygon",
              "coordinates": [
                [
                  [
                    16.88633,
                    48.121292
                  ],
                  [
                    16.885418,
                    48.121929
                  ],
                  [
                    16.883712,
                    48.120926
                  ],
                  [
                    16.884903,
                    48.120167
                  ],
                  [
                    16.88633,
                    48.121292
                  ]
                ]
              ]
            }
          }
        ]
      }
    },
    "Canabae": {
      "color": "#9b59b6",
      "geojson": {
        "type": "FeatureCollection",
        "features": [
          {
            "type": "Feature",
            "properties": {
              "layer": "Canabae"
            },
            "geometry": {
              "type": "Polygon",
              "coordinates": [
                [
                  [
                    16.892402,
                    48.127802
                  ],
                  [
                    16.892874,
                    48.129048
                  ],
                  [
                    16.893668,
                    48.129205
                  ],
                  [
                    16.894119,
                    48.129406
                  ],
                  [
                    16.895363,
                    48.129621
                  ],
                  [
                    16.895857,
                    48.129492
                  ],
                  [
                    16.896758,
                    48.129907
                  ],
                  [
                    16.898475,
                    48.129191
                  ],
                  [
                    16.899204,
                    48.12952
                  ],
                  [
                    16.900427,
                    48.129277
                  ],
                  [
                    16.899869,
                    48.128475
                  ],
                  [
                    16.901972,
                    48.127859
                  ],
                  [
                    16.901972,
                    48.127257
                  ],
                  [
                    16.9015,
                    48.126856
                  ],
                  [
                    16.900771,
                    48.126427
                  ],
                  [
                    16.900084,
                    48.12624
                  ],
                  [
                    16.899354,
                    48.125768
                  ],
                  [
                    16.898646,
                    48.125438
                  ],
                  [
                    16.89841,
                    48.124908
                  ],
                  [
                    16.898539,
                    48.124436
                  ],
                  [
                    16.899805,
                    48.123863
                  ],
                  [
                    16.900363,
                    48.123404
                  ],
                  [
                    16.900213,
                    48.122817
                  ],
                  [
                    16.900127,
                    48.122302
                  ],
                  [
                    16.898797,
                    48.121098
                  ],
                  [
                    16.897445,
                    48.121156
                  ],
                  [
                    16.896844,
                    48.120669
                  ],
                  [
                    16.897166,
                    48.119809
                  ],
                  [
                    16.89826,
                    48.119122
                  ],
                  [
                    16.897337,
                    48.118592
                  ],
                  [
                    16.896887,
                    48.117976
                  ],
                  [
                    16.898003,
                    48.117259
                  ],
                  [
                    16.897852,
                    48.116615
                  ],
                  [
                    16.895299,
                    48.118162
                  ],
                  [
                    16.893218,
                    48.117044
                  ],
                  [
                    16.889977,
                    48.118606
                  ],
                  [
                    16.889656,
                    48.118749
                  ],
                  [
                    16.889312,
                    48.118477
                  ],
                  [
                    16.88972,
                    48.118033
                  ],
                  [
                    16.889441,
                    48.117746
                  ],
                  [
                    16.888797,
                    48.11756
                  ],
                  [
                    16.888239,
                    48.117259
                  ],
                  [
                    16.887639,
                    48.117474
                  ],
                  [
                    16.887038,
                    48.117288
                  ],
                  [
                    16.887488,
                    48.116858
                  ],
                  [
                    16.887188,
                    48.116557
                  ],
                  [
                    16.887853,
                    48.116185
                  ],
                  [
                    16.887488,
                    48.115712
                  ],
                  [
                    16.887081,
                    48.11534
                  ],
                  [
                    16.886523,
                    48.115512
                  ],
                  [
                    16.8859,
                    48.115139
                  ],
                  [
                    16.885343,
                    48.116686
                  ],
                  [
                    16.887574,
                    48.118405
                  ],
                  [
                    16.890471,
                    48.11968
                  ],
                  [
                    16.895471,
                    48.122402
                  ],
                  [
                    16.89693,
                    48.123548
                  ],
                  [
                    16.895213,
                    48.123934
                  ],
                  [
                    16.895921,
                    48.125395
                  ],
                  [
                    16.89281,
                    48.127615
                  ],
                  [
                    16.892402,
                    48.127802
                  ]
                ]
              ]
            }
          },
          {
            "type": "Feature",
            "properties": {
              "layer": "Canabae"
            },
            "geometry": {
              "type": "Polygon",
              "coordinates": [
                [
                  [
                    16.843586,
                    48.114108
                  ],
                  [
                    16.840754,
                    48.113907
                  ],
                  [
                    16.840625,
                    48.114251
                  ],
                  [
                    16.844316,
                    48.114881
                  ],
                  [
                    16.847792,
                    48.115741
                  ],
                  [
                    16.849637,
                    48.115741
                  ],
                  [
                    16.849594,
                    48.117001
                  ],
                  [
                    16.858606,
                    48.117001
                  ],
                  [
                    16.863627,
                    48.116285
                  ],
                  [
                    16.863756,
                    48.115769
                  ],
                  [
                    16.866803,
                    48.115712
                  ],
                  [
                    16.868091,
                    48.114967
                  ],
                  [
                    16.865945,
                    48.114366
                  ],
                  [
                    16.865602,
                    48.112847
                  ],
                  [
                    16.864486,
                    48.112503
                  ],
                  [
                    16.863585,
                    48.112876
                  ],
                  [
                    16.858521,
                    48.112274
                  ],
                  [
                    16.855474,
                    48.11236
                  ],
                  [
                    16.849766,
                    48.113506
                  ],
                  [
                    16.849551,
                    48.11428
                  ],
                  [
                    16.847706,
                    48.114423
                  ],
                  [
                    16.845474,
                    48.114136
                  ],
                  [
                    16.842513,
                    48.113449
                  ],
                  [
                    16.842556,
                    48.113936
                  ],
                  [
                    16.843586,
                    48.114108
                  ]
                ]
              ]
            }
          }
        ]
      }
    },
    "Gräberbezirk1": {
      "color": "#1abc9c",
      "geojson": {
        "type": "FeatureCollection",
        "features": [
          {
            "type": "Feature",
            "properties": {
              "layer": "Gräberbezirk1"
            },
            "geometry": {
              "type": "Polygon",
              "coordinates": [
                [
                  [
                    16.864014,
                    48.112159
                  ],
                  [
                    16.864829,
                    48.110497
                  ],
                  [
                    16.864614,
                    48.108377
                  ],
                  [
                    16.865001,
                    48.107059
                  ],
                  [
                    16.864829,
                    48.105454
                  ],
                  [
                    16.861439,
                    48.10766
                  ],
                  [
                    16.860752,
                    48.110841
                  ],
                  [
                    16.861567,
                    48.111987
                  ],
                  [
                    16.864014,
                    48.112159
                  ]
                ]
              ]
            }
          }
        ]
      }
    },
    "Gräberbezirk2": {
      "color": "#e67e22",
      "geojson": {
        "type": "FeatureCollection",
        "features": [
          {
            "type": "Feature",
            "properties": {
              "layer": "Gräberbezirk2"
            },
            "geometry": {
              "type": "Polygon",
              "coordinates": [
                [
                  [
                    16.852298,
                    48.111901
                  ],
                  [
                    16.85277,
                    48.11107
                  ],
                  [
                    16.851826,
                    48.110067
                  ],
                  [
                    16.851182,
                    48.10938
                  ],
                  [
                    16.850324,
                    48.109609
                  ],
                  [
                    16.84998,
                    48.110211
                  ],
                  [
                    16.848779,
                    48.109552
                  ],
                  [
                    16.847663,
                    48.108176
                  ],
                  [
                    16.84762,
                    48.107145
                  ],
                  [
                    16.848435,
                    48.106858
                  ],
                  [
                    16.849551,
                    48.10597
                  ],
                  [
                    16.851611,
                    48.107546
                  ],
                  [
                    16.854916,
                    48.105826
                  ],
                  [
                    16.856503,
                    48.107603
                  ],
                  [
                    16.857533,
                    48.107288
                  ],
                  [
                    16.859293,
                    48.106543
                  ],
                  [
                    16.86058,
                    48.106973
                  ],
                  [
                    16.858048,
                    48.109666
                  ],
                  [
                    16.85689,
                    48.110727
                  ],
                  [
                    16.85792,
                    48.111873
                  ],
                  [
                    16.855087,
                    48.112073
                  ],
                  [
                    16.852298,
                    48.111901
                  ]
                ]
              ]
            }
          }
        ]
      }
    },
    "Canabae, westlich": {
      "color": "#34495e",
      "geojson": {
        "type": "FeatureCollection",
        "features": [
          {
            "type": "Feature",
            "properties": {
              "layer": "Canabae, westlich"
            },
            "geometry": {
              "type": "Polygon",
              "coordinates": [
                [
                  [
                    16.884785,
                    48.119995
                  ],
                  [
                    16.883519,
                    48.120833
                  ],
                  [
                    16.88059,
                    48.11872
                  ],
                  [
                    16.876523,
                    48.116292
                  ],
                  [
                    16.877757,
                    48.116328
                  ],
                  [
                    16.880171,
                    48.116951
                  ],
                  [
                    16.882124,
                    48.117574
                  ],
                  [
                    16.884785,
                    48.119995
                  ]
                ]
              ]
            }
          }
        ]
      }
    },
    "Gräberbezirk3": {
      "color": "#e74c3c",
      "geojson": {
        "type": "FeatureCollection",
        "features": [
          {
            "type": "Feature",
            "properties": {
              "layer": "Gräberbezirk3"
            },
            "geometry": {
              "type": "Polygon",
              "coordinates": [
                [
                  [
                    16.842406,
                    48.113893
                  ],
                  [
                    16.840603,
                    48.113721
                  ],
                  [
                    16.84011,
                    48.113979
                  ],
                  [
                    16.837792,
                    48.113649
                  ],
                  [
                    16.831055,
                    48.111973
                  ],
                  [
                    16.831205,
                    48.111715
                  ],
                  [
                    16.837192,
                    48.112632
                  ],
                  [
                    16.839509,
                    48.112704
                  ],
                  [
                    16.839981,
                    48.113277
                  ],
                  [
                    16.842406,
                    48.113449
                  ],
                  [
                    16.842406,
                    48.113893
                  ]
                ]
              ]
            }
          }
        ]
      }
    },
    "Gräberbezirk4": {
      "color": "#3498db",
      "geojson": {
        "type": "FeatureCollection",
        "features": [
          {
            "type": "Feature",
            "properties": {
              "layer": "Gräberbezirk4"
            },
            "geometry": {
              "type": "Polygon",
              "coordinates": [
                [
                  [
                    16.900878,
                    48.11448
                  ],
                  [
                    16.90414,
                    48.114337
                  ],
                  [
                    16.901779,
                    48.111873
                  ],
                  [
                    16.900406,
                    48.112962
                  ],
                  [
                    16.899419,
                    48.112904
                  ],
                  [
                    16.899676,
                    48.113563
                  ],
                  [
                    16.900878,
                    48.11448
                  ]
                ]
              ]
            }
          }
        ]
      }
    },
    "Gräberbezirk5": {
      "color": "#2ecc71",
      "geojson": {
        "type": "FeatureCollection",
        "features": [
          {
            "type": "Feature",
            "properties": {
              "layer": "Gräberbezirk5"
            },
            "geometry": {
              "type": "Polygon",
              "coordinates": [
                [
                  [
                    16.902208,
                    48.132213
                  ],
                  [
                    16.902723,
                    48.131869
                  ],
                  [
                    16.900706,
                    48.129864
                  ],
                  [
                    16.899333,
                    48.129578
                  ],
                  [
                    16.898561,
                    48.129348
                  ],
                  [
                    16.89796,
                    48.12952
                  ],
                  [
                    16.898303,
                    48.130122
                  ],
                  [
                    16.900105,
                    48.131325
                  ],
                  [
                    16.901264,
                    48.131926
                  ],
                  [
                    16.902208,
                    48.132213
                  ]
                ]
              ]
            }
          }
        ]
      }
    }
  }
}